processmodel.py
processmodel-0.1.0.dist-info/licenses/LICENSE
processmodel-0.1.0.dist-info/METADATA
processmodel-0.1.0.dist-info/WHEEL
processmodel-0.1.0.dist-info/top_level.txt
processmodel-0.1.0.dist-info/RECORD
