Metadata-Version: 2.4
Name: ProcessModel
Version: 0.1.0
Summary: A framework built on PyTorch for eco-hydrological modeling
Author-email: Long Jiang <jlon@uw.edu>
License: MIT License
Keywords: hydrology,ecohydro,modeling
Classifier: Programming Language :: Python :: 3
Classifier: License :: OSI Approved :: MIT License
Classifier: Operating System :: OS Independent
Requires-Python: >=3.9
License-File: LICENSE
Requires-Dist: numpy<2.0,>=1.23
Requires-Dist: pandas>=2.0
Requires-Dist: torch>=2.2
Requires-Dist: torch-geometric>=2.5
Requires-Dist: matplotlib>=3.7
Requires-Dist: networkx>=3.0
Requires-Dist: pysheds>=0.3
Requires-Dist: pyproj>=3.6
Requires-Dist: tensordict>=0.2
Dynamic: license-file
